{"F1": {"Name": "F1", "TimeY": 9999, "TimeM": 0, "TimeD": 0, "CanDie": 1}, "F2": {"Name": "F2", "TimeY": 0, "TimeM": 1, "TimeD": 0, "CanDie": 1}, "F11": {"Name": "F11", "TimeY": 9999, "TimeM": 0, "TimeD": 0, "CanDie": 1}, "F12": {"Name": "F12", "TimeY": 9999, "TimeM": 0, "TimeD": 0, "CanDie": 1}, "F14": {"Name": "F14", "TimeY": 9999, "TimeM": 0, "TimeD": 0, "CanDie": 1}, "F15": {"Name": "F15", "TimeY": 9999, "TimeM": 0, "TimeD": 0, "CanDie": 1}, "F16": {"Name": "F16", "TimeY": 9999, "TimeM": 0, "TimeD": 0, "CanDie": 1}, "F26": {"Name": "F26", "TimeY": 9999, "TimeM": 0, "TimeD": 0, "CanDie": 1}, "F27": {"Name": "F27", "TimeY": 9999, "TimeM": 0, "TimeD": 0, "CanDie": 1}, "F50": {"Name": "F50", "TimeY": 9999, "TimeM": 0, "TimeD": 0, "CanDie": 1}, "F51": {"Name": "F51", "TimeY": 9999, "TimeM": 0, "TimeD": 0, "CanDie": 1}, "F60": {"Name": "F60", "TimeY": 9999, "TimeM": 0, "TimeD": 0, "CanDie": 1}, "F61": {"Name": "F61", "TimeY": 9999, "TimeM": 0, "TimeD": 0, "CanDie": 1}, "F62": {"Name": "F62", "TimeY": 9999, "TimeM": 0, "TimeD": 0, "CanDie": 1}, "F63": {"Name": "F63", "TimeY": 9999, "TimeM": 0, "TimeD": 0, "CanDie": 1}, "F64": {"Name": "F64", "TimeY": 9999, "TimeM": 0, "TimeD": 0, "CanDie": 1}, "F65": {"Name": "F65", "TimeY": 9999, "TimeM": 0, "TimeD": 0, "CanDie": 1}, "F66": {"Name": "F66", "TimeY": 9999, "TimeM": 0, "TimeD": 0, "CanDie": 1}, "F67": {"Name": "F67", "TimeY": 9999, "TimeM": 0, "TimeD": 0, "CanDie": 1}, "F70": {"Name": "F70", "TimeY": 9999, "TimeM": 0, "TimeD": 0, "CanDie": 1}, "F90": {"Name": "F90", "TimeY": 9999, "TimeM": 0, "TimeD": 0, "CanDie": 1}, "F91": {"Name": "F91", "TimeY": 9999, "TimeM": 0, "TimeD": 0, "CanDie": 1}, "F92": {"Name": "F92", "TimeY": 9999, "TimeM": 0, "TimeD": 0, "CanDie": 1}, "F93": {"Name": "F93", "TimeY": 9999, "TimeM": 0, "TimeD": 0, "CanDie": 1}, "F94": {"Name": "F94", "TimeY": 9999, "TimeM": 0, "TimeD": 0, "CanDie": 1}, "F95": {"Name": "F95", "TimeY": 9999, "TimeM": 0, "TimeD": 0, "CanDie": 1}, "F96": {"Name": "F96", "TimeY": 9999, "TimeM": 0, "TimeD": 0, "CanDie": 1}, "F97": {"Name": "F97", "TimeY": 9999, "TimeM": 0, "TimeD": 0, "CanDie": 1}, "F98": {"Name": "F98", "TimeY": 9999, "TimeM": 0, "TimeD": 0, "CanDie": 1}, "F99": {"Name": "F99", "TimeY": 9999, "TimeM": 0, "TimeD": 0, "CanDie": 1}, "F100": {"Name": "F100", "TimeY": 9999, "TimeM": 0, "TimeD": 0, "CanDie": 1}, "F101": {"Name": "F101", "TimeY": 0, "TimeM": 1, "TimeD": 0, "CanDie": 1}, "F111": {"Name": "F111", "TimeY": 9999, "TimeM": 0, "TimeD": 0, "CanDie": 1}, "F121": {"Name": "F121", "TimeY": 9999, "TimeM": 0, "TimeD": 0, "CanDie": 1}, "F141": {"Name": "F141", "TimeY": 9999, "TimeM": 0, "TimeD": 0, "CanDie": 1}, "F151": {"Name": "F151", "TimeY": 9999, "TimeM": 0, "TimeD": 0, "CanDie": 1}, "F161": {"Name": "F161", "TimeY": 9999, "TimeM": 0, "TimeD": 0, "CanDie": 1}, "F162": {"Name": "F162", "TimeY": 9999, "TimeM": 0, "TimeD": 0, "CanDie": 1}, "F163": {"Name": "F163", "TimeY": 9999, "TimeM": 0, "TimeD": 0, "CanDie": 1}, "F164": {"Name": "F164", "TimeY": 9999, "TimeM": 0, "TimeD": 0, "CanDie": 1}, "F165": {"Name": "F165", "TimeY": 9999, "TimeM": 0, "TimeD": 0, "CanDie": 1}, "F166": {"Name": "F166", "TimeY": 9999, "TimeM": 0, "TimeD": 0, "CanDie": 1}, "F167": {"Name": "F167", "TimeY": 9999, "TimeM": 0, "TimeD": 0, "CanDie": 1}, "F180": {"Name": "F180", "TimeY": 9999, "TimeM": 0, "TimeD": 0, "CanDie": 1}, "Sea2": {"Name": "Sea2", "TimeY": 9999, "TimeM": 0, "TimeD": 0, "CanDie": 1}, "Sea3": {"Name": "Sea3", "TimeY": 9999, "TimeM": 0, "TimeD": 0, "CanDie": 1}, "Sea4": {"Name": "Sea4", "TimeY": 9999, "TimeM": 0, "TimeD": 0, "CanDie": 1}, "Sea5": {"Name": "Sea5", "TimeY": 9999, "TimeM": 0, "TimeD": 0, "CanDie": 1}, "Sea6": {"Name": "Sea6", "TimeY": 9999, "TimeM": 0, "TimeD": 0, "CanDie": 1}, "Sea7": {"Name": "Sea7", "TimeY": 9999, "TimeM": 0, "TimeD": 0, "CanDie": 1}, "Sea8": {"Name": "Sea8", "TimeY": 9999, "TimeM": 0, "TimeD": 0, "CanDie": 1}, "Sea9": {"Name": "Sea9", "TimeY": 9999, "TimeM": 0, "TimeD": 0, "CanDie": 1}, "Sea10": {"Name": "Sea10", "TimeY": 9999, "TimeM": 0, "TimeD": 0, "CanDie": 1}, "Sea11": {"Name": "Sea11", "TimeY": 9999, "TimeM": 0, "TimeD": 0, "CanDie": 1}, "Sea12": {"Name": "Sea12", "TimeY": 9999, "TimeM": 0, "TimeD": 0, "CanDie": 1}, "Sea13": {"Name": "Sea13", "TimeY": 9999, "TimeM": 0, "TimeD": 0, "CanDie": 1}, "Sea14": {"Name": "Sea14", "TimeY": 9999, "TimeM": 0, "TimeD": 0, "CanDie": 1}, "Sea15": {"Name": "Sea15", "TimeY": 9999, "TimeM": 0, "TimeD": 0, "CanDie": 1}, "Sea16": {"Name": "Sea16", "TimeY": 9999, "TimeM": 0, "TimeD": 0, "CanDie": 1}, "Sea17": {"Name": "Sea17", "TimeY": 9999, "TimeM": 0, "TimeD": 0, "CanDie": 1}, "Sea18": {"Name": "Sea18", "TimeY": 9999, "TimeM": 0, "TimeD": 0, "CanDie": 1}}