{"2096": {"skillid": 2096, "value1": [48], "value2": [27], "value3": [1]}, "2097": {"skillid": 2097, "value1": [48], "value2": [27], "value3": [1]}, "2098": {"skillid": 2098, "value1": [48], "value2": [27], "value3": [1]}, "2099": {"skillid": 2099, "value1": [48], "value2": [27], "value3": [1]}, "2100": {"skillid": 2100, "value1": [48], "value2": [27], "value3": [1]}, "2101": {"skillid": 2101, "value1": [48], "value2": [996], "value3": [3]}, "2102": {"skillid": 2102, "value1": [48], "value2": [996], "value3": [4]}, "2103": {"skillid": 2103, "value1": [48], "value2": [996], "value3": [5]}, "2104": {"skillid": 2104, "value1": [48], "value2": [996], "value3": [6]}, "2105": {"skillid": 2105, "value1": [48], "value2": [996], "value3": [6]}, "2111": {"skillid": 2111, "value1": [49], "value2": [913], "value3": [1]}, "2112": {"skillid": 2112, "value1": [49], "value2": [913], "value3": [1]}, "2113": {"skillid": 2113, "value1": [49], "value2": [913], "value3": [1]}, "2114": {"skillid": 2114, "value1": [49], "value2": [913], "value3": [1]}, "2115": {"skillid": 2115, "value1": [49], "value2": [913], "value3": [1]}, "2116": {"skillid": 2116, "value1": [49], "value2": [44], "value3": [1]}, "2117": {"skillid": 2117, "value1": [49], "value2": [44], "value3": [1]}, "2118": {"skillid": 2118, "value1": [49], "value2": [44], "value3": [1]}, "2119": {"skillid": 2119, "value1": [49], "value2": [44], "value3": [1]}, "2120": {"skillid": 2120, "value1": [49], "value2": [44], "value3": [1]}, "2121": {"skillid": 2121, "value1": [49], "value2": [44], "value3": [1]}, "2122": {"skillid": 2122, "value1": [49], "value2": [44], "value3": [1]}, "2123": {"skillid": 2123, "value1": [49], "value2": [44], "value3": [1]}, "2124": {"skillid": 2124, "value1": [49], "value2": [44], "value3": [1]}, "2125": {"skillid": 2125, "value1": [49], "value2": [44], "value3": [1]}, "2126": {"skillid": 2126, "value1": [27], "value2": [996], "value3": [1]}, "2127": {"skillid": 2127, "value1": [27], "value2": [996], "value3": [2]}, "2128": {"skillid": 2128, "value1": [27], "value2": [996], "value3": [3]}, "2129": {"skillid": 2129, "value1": [27], "value2": [996], "value3": [4]}, "2130": {"skillid": 2130, "value1": [27], "value2": [996], "value3": [5]}, "2131": {"skillid": 2131, "value1": [48, 49], "value2": [27, 44], "value3": [1, 1]}, "2132": {"skillid": 2132, "value1": [48, 49], "value2": [27, 44], "value3": [1, 1]}, "2133": {"skillid": 2133, "value1": [48, 49], "value2": [27, 44], "value3": [1, 1]}, "2134": {"skillid": 2134, "value1": [48, 49], "value2": [27, 44], "value3": [1, 1]}, "2135": {"skillid": 2135, "value1": [48, 49], "value2": [27, 44], "value3": [1, 1]}, "3141": {"skillid": 3141, "value1": [19], "value2": [23], "value3": [1]}, "3142": {"skillid": 3142, "value1": [19], "value2": [23], "value3": [1]}, "3143": {"skillid": 3143, "value1": [19], "value2": [23], "value3": [1]}, "3144": {"skillid": 3144, "value1": [19], "value2": [23], "value3": [1]}, "3145": {"skillid": 3145, "value1": [19], "value2": [23], "value3": [1]}, "4021": {"skillid": 4021, "value1": [26], "value2": [5], "value3": [1]}, "4022": {"skillid": 4022, "value1": [26], "value2": [5], "value3": [1]}, "4023": {"skillid": 4023, "value1": [26], "value2": [5], "value3": [1]}, "4024": {"skillid": 4024, "value1": [26], "value2": [5], "value3": [1]}, "4025": {"skillid": 4025, "value1": [26], "value2": [5], "value3": [1]}, "4051": {"skillid": 4051, "value1": [26], "value2": [977], "value3": [1]}, "4052": {"skillid": 4052, "value1": [26], "value2": [977], "value3": [1]}, "4053": {"skillid": 4053, "value1": [26], "value2": [977], "value3": [1]}, "4054": {"skillid": 4054, "value1": [26], "value2": [977], "value3": [1]}, "4055": {"skillid": 4055, "value1": [26], "value2": [977], "value3": [1]}, "4066": {"skillid": 4066, "value1": [26], "value2": [5], "value3": [2]}, "4067": {"skillid": 4067, "value1": [26], "value2": [5], "value3": [2]}, "4068": {"skillid": 4068, "value1": [26], "value2": [5], "value3": [2]}, "4069": {"skillid": 4069, "value1": [26], "value2": [5], "value3": [2]}, "4070": {"skillid": 4070, "value1": [26], "value2": [5], "value3": [2]}, "4121": {"skillid": 4121, "value1": [26], "value2": [958], "value3": [1]}, "4122": {"skillid": 4122, "value1": [26], "value2": [958], "value3": [1]}, "4123": {"skillid": 4123, "value1": [26], "value2": [958], "value3": [1]}, "4124": {"skillid": 4124, "value1": [26], "value2": [958], "value3": [1]}, "4125": {"skillid": 4125, "value1": [26], "value2": [958], "value3": [1]}, "4126": {"skillid": 4126, "value1": [5], "value2": [26], "value3": [1]}, "4127": {"skillid": 4127, "value1": [5], "value2": [26], "value3": [1]}, "4128": {"skillid": 4128, "value1": [5], "value2": [26], "value3": [1]}, "4129": {"skillid": 4129, "value1": [5], "value2": [26], "value3": [1]}, "4130": {"skillid": 4130, "value1": [5], "value2": [26], "value3": [1]}, "5306": {"skillid": 5306, "value1": [4167], "value2": [4168], "value3": [1]}, "5307": {"skillid": 5307, "value1": [4167], "value2": [4168], "value3": [1]}, "5308": {"skillid": 5308, "value1": [4167], "value2": [4168], "value3": [1]}, "5309": {"skillid": 5309, "value1": [4167], "value2": [4168], "value3": [1]}, "5310": {"skillid": 5310, "value1": [4167], "value2": [4168], "value3": [1]}, "6066": {"skillid": 6066, "value1": [6024], "value2": [847], "value3": [1]}, "6067": {"skillid": 6067, "value1": [6024], "value2": [847], "value3": [1]}, "6068": {"skillid": 6068, "value1": [6024], "value2": [847], "value3": [1]}, "6069": {"skillid": 6069, "value1": [6024], "value2": [847], "value3": [1]}, "6070": {"skillid": 6070, "value1": [6024], "value2": [847], "value3": [1]}, "7086": {"skillid": 7086, "value1": [27], "value2": [5], "value3": [4]}, "7087": {"skillid": 7087, "value1": [27], "value2": [5], "value3": [4]}, "7088": {"skillid": 7088, "value1": [27], "value2": [5], "value3": [4]}, "7089": {"skillid": 7089, "value1": [27], "value2": [5], "value3": [4]}, "7090": {"skillid": 7090, "value1": [27], "value2": [5], "value3": [4]}, "20486": {"skillid": 20486, "value1": [9215], "value2": [9216], "value3": [1]}, "20487": {"skillid": 20487, "value1": [9215], "value2": [9216], "value3": [1]}, "20488": {"skillid": 20488, "value1": [9215], "value2": [9216], "value3": [1]}, "20489": {"skillid": 20489, "value1": [9215], "value2": [9216], "value3": [1]}, "20490": {"skillid": 20490, "value1": [9215], "value2": [9216], "value3": [1]}}